odoo9_addon_pos_accented_search-9.0.0.0.2-nspkg.pth
odoo_addons/pos_accented_search/README.rst
odoo_addons/pos_accented_search/__init__.py
odoo_addons/pos_accented_search/__openerp__.py
odoo_addons/pos_accented_search/i18n/pos_accented_search.pot
odoo_addons/pos_accented_search/readme/CONTRIBUTORS.rst
odoo_addons/pos_accented_search/readme/DESCRIPTION.rst
odoo_addons/pos_accented_search/readme/USAGE.rst
odoo_addons/pos_accented_search/static/description/icon.png
odoo_addons/pos_accented_search/static/description/index.html
odoo_addons/pos_accented_search/static/src/js/db.js
odoo_addons/pos_accented_search/views/templates.xml
odoo9_addon_pos_accented_search-9.0.0.0.2.dist-info/METADATA
odoo9_addon_pos_accented_search-9.0.0.0.2.dist-info/WHEEL
odoo9_addon_pos_accented_search-9.0.0.0.2.dist-info/namespace_packages.txt
odoo9_addon_pos_accented_search-9.0.0.0.2.dist-info/top_level.txt
odoo9_addon_pos_accented_search-9.0.0.0.2.dist-info/RECORD
