Metadata-Version: 2.1
Name: odoo9-addon-pos-accented-search
Version: 9.0.0.0.2
Summary: Point of Sale - Product search works regardless of accented characters
Home-page: https://github.com/OCA/pos
Author: Le Nid, Odoo Community Association (OCA)
Author-email: support@odoo-community.org
License: AGPL-3
Platform: UNKNOWN
Classifier: Programming Language :: Python
Classifier: Framework :: Odoo
Classifier: License :: OSI Approved :: GNU Affero General Public License v3
Requires-Python: ~=2.7
Requires-Dist: odoo (<9.1a,>=9.0a)
